{
  "miniprogramRoot": "miniprogram/",
  "cloudfunctionRoot": "cloudfunctions/",
  "setting": {
    "urlCheck": true,
    "es6": true,
    "enhance": false,
    "postcss": true,
    "preloadBackgroundData": false,
    "minified": true,
    "newFeature": true,
    "coverView": true,
    "nodeModules": false,
    "autoAudits": false,
    "showShadowRootInWxmlPanel": true,
    "scopeDataCheck": false,
    "uglifyFileName": false,
    "checkInvalidKey": true,
    "checkSiteMap": true,
    "uploadWithSourceMap": true,
    "compileHotReLoad": false,
    "useMultiFrameRuntime": false,
    "useApiHook": true,
    "babelSetting": {
      "ignore": [],
      "disablePlugins": [],
      "outputPath": ""
    },
    "enableEngineNative": false,
    "bundle": false,
    "useIsolateContext": true,
    "useCompilerModule": true,
    "userConfirmedUseCompilerModuleSwitch": false,
    "userConfirmedBundleSwitch": false,
    "packNpmManually": false,
    "packNpmRelationList": [],
    "minifyWXSS": true
  },
  "appid": "wxd59e94e53a2d9a99",
  "projectname": "GarbageSort%20e",
  "libVersion": "2.9.3",
  "simulatorType": "wechat",
  "simulatorPluginLibVersion": {},
  "cloudfunctionTemplateRoot": "cloudfunctionTemplate",
  "condition": {
    "search": {
      "list": []
    },
    "conversation": {
      "list": []
    },
    "plugin": {
      "list": []
    },
    "game": {
      "list": []
    },
    "miniprogram": {
      "list": [
        {
          "id": -1,
          "name": "db guide",
          "pathName": "pages/databaseGuide/databaseGuide",
          "query": ""
        },
        {
          "id": -1,
          "name": "分类",
          "pathName": "pages/sort/sort",
          "query": "",
          "scene": null
        },
        {
          "id": -1,
          "name": "拍照页面",
          "pathName": "pages/ai/camera/camera",
          "query": "",
          "scene": null
        },
        {
          "id": -1,
          "name": "搜索",
          "pathName": "pages/ai/search",
          "query": "",
          "scene": null
        },
        {
          "id": 4,
          "name": "筛选",
          "pathName": "pages/ai/filter/filter",
          "query": "type=3",
          "scene": null
        },
        {
          "id": 5,
          "name": "ai 搜索结果",
          "pathName": "pages/result/gan",
          "query": "keyword=花",
          "scene": null
        },
        {
          "id": 6,
          "name": "未查询到的结果提交",
          "pathName": "pages/result/commit",
          "query": "keyword=花",
          "scene": null
        }
      ]
    }
  }
}